odoo/addons/l10n_fr_account_invoice_facturx/README.rst
odoo/addons/l10n_fr_account_invoice_facturx/__init__.py
odoo/addons/l10n_fr_account_invoice_facturx/__manifest__.py
odoo/addons/l10n_fr_account_invoice_facturx/i18n/l10n_fr_account_invoice_factur-x.pot
odoo/addons/l10n_fr_account_invoice_facturx/i18n/l10n_fr_account_invoice_facturx.pot
odoo/addons/l10n_fr_account_invoice_facturx/models/__init__.py
odoo/addons/l10n_fr_account_invoice_facturx/models/account_invoice.py
odoo/addons/l10n_fr_account_invoice_facturx/readme/CONTRIBUTORS.rst
odoo/addons/l10n_fr_account_invoice_facturx/readme/DESCRIPTION.rst
odoo/addons/l10n_fr_account_invoice_facturx/static/description/icon.png
odoo/addons/l10n_fr_account_invoice_facturx/static/description/index.html
odoo12_addon_l10n_fr_account_invoice_facturx-12.0.1.0.0.99.dev3.dist-info/METADATA
odoo12_addon_l10n_fr_account_invoice_facturx-12.0.1.0.0.99.dev3.dist-info/WHEEL
odoo12_addon_l10n_fr_account_invoice_facturx-12.0.1.0.0.99.dev3.dist-info/top_level.txt
odoo12_addon_l10n_fr_account_invoice_facturx-12.0.1.0.0.99.dev3.dist-info/RECORD
